{   "getting_started": {
        "title": "Advanced world creation: Start here"
    },
    "how": {
        "title": "How to ...",
        "children": ["objects", "random", "background", "custom_goals"]
    },
        "objects": {
            "title": "How to add objects and goals"
        },
        "random": {
            "title": "How to add some randomness"
        },
        "background" :{
            "title": "How to work with Background tiles, obstacles and decorative objects"
        },
        "custom_goals": {
            "title": "How to set up a custom goal"
        },
    "why": {
        "title": "Why? Understanding some design and other decisions",
        "children": ["motivation", "nobreak"]
    },
        "motivation": {
            "title": "Motivation: why create more complex worlds?"
        },
        "nobreak": {
            "title": "Why are non-breaking spaces removed in Python code?"
        },
    "reference": {
        "title": "Reference",
        "children": ["editors", "naming_convention", "animated"]
    },
        "editors" : {
            "title": "The many different editors"
        },
        "naming_convention" : {
            "title": "Naming convention"
        },
        "animated": {
            "title": "Animated images"
        },
    "canvases": {
        "title": "Layers and canvases"
    },
    "todo" : {
        "title": "To do"
    }
}